vennam/Analysis.py
vennam/DataBase.py
vennam/DataFrameToDict.py
vennam/__init__.py
vennam-1.2.11.dist-info/LICENSE.txt
vennam-1.2.11.dist-info/METADATA
vennam-1.2.11.dist-info/WHEEL
vennam-1.2.11.dist-info/top_level.txt
vennam-1.2.11.dist-info/RECORD
