Metadata-Version: 2.1
Name: vennam
Version: 1.2.11
Summary: This package will helps to convert DataFrame to Dictionary and provide Exploratory Data Analysis.
Home-page: https://github.com/deva567/vennam
Author: Vennam
Author-email: vennamdevendhar@gmail.com
License: MIT
Platform: UNKNOWN
Classifier: License :: OSI Approved :: MIT License
Classifier: Programming Language :: Python
Classifier: Programming Language :: Python :: 3
Classifier: Programming Language :: Python :: 3.7
Requires-Dist: pandas (>=1.0.5)
Requires-Dist: wordcloud (>=1.7.0)
Requires-Dist: nltk (>=3.5)
Requires-Dist: matplotlib (>=3.2.2)
Requires-Dist: Pillow (>=7.1.2)
Requires-Dist: psycopg2 (>=2.8.5)
Requires-Dist: sqlalchemy (>=1.3.17)
